nexcsi/__init__.py
nexcsi/_decoder.py
nexcsi/floating.py
nexcsi/interleaved.py
nexcsi-0.5.1.dist-info/WHEEL
nexcsi-0.5.1.dist-info/METADATA
nexcsi-0.5.1.dist-info/RECORD
